odoo/addons/mail_template_multi_company/README.rst
odoo/addons/mail_template_multi_company/__init__.py
odoo/addons/mail_template_multi_company/__manifest__.py
odoo/addons/mail_template_multi_company/i18n/es.po
odoo/addons/mail_template_multi_company/i18n/it.po
odoo/addons/mail_template_multi_company/i18n/mail_template_multi_company.pot
odoo/addons/mail_template_multi_company/models/__init__.py
odoo/addons/mail_template_multi_company/models/ir_model_data.py
odoo/addons/mail_template_multi_company/models/mail_template.py
odoo/addons/mail_template_multi_company/readme/CONFIGURE.rst
odoo/addons/mail_template_multi_company/readme/CONTRIBUTORS.rst
odoo/addons/mail_template_multi_company/readme/DESCRIPTION.rst
odoo/addons/mail_template_multi_company/readme/USAGE.rst
odoo/addons/mail_template_multi_company/security/mail_template.xml
odoo/addons/mail_template_multi_company/static/description/icon.png
odoo/addons/mail_template_multi_company/static/description/index.html
odoo/addons/mail_template_multi_company/tests/__init__.py
odoo/addons/mail_template_multi_company/tests/test_ir_model_data.py
odoo/addons/mail_template_multi_company/views/mail_template.xml
odoo14_addon_mail_template_multi_company-14.0.1.1.1.dist-info/METADATA
odoo14_addon_mail_template_multi_company-14.0.1.1.1.dist-info/WHEEL
odoo14_addon_mail_template_multi_company-14.0.1.1.1.dist-info/top_level.txt
odoo14_addon_mail_template_multi_company-14.0.1.1.1.dist-info/RECORD
